polls/__init__.py
polls/admin.py
polls/models.py
polls/serializers.py
polls/tests.py
polls/urls.py
polls/views.py
polls/migrations/0001_initial.py
polls/migrations/0002_auto_20151005_1920.py
polls/migrations/__init__.py
polls/templatetags/__init__.py
polls/templatetags/polls.py
wagtail_polls/__init__.py
wagtail_polls/settings.py
wagtail_polls/urls.py
wagtail_polls/wsgi.py
wagtail_polls-2.1.0.dist-info/LICENSE
wagtail_polls-2.1.0.dist-info/METADATA
wagtail_polls-2.1.0.dist-info/WHEEL
wagtail_polls-2.1.0.dist-info/top_level.txt
wagtail_polls-2.1.0.dist-info/RECORD
