Metadata-Version: 2.1
Name: wagtail-polls
Version: 2.1.0
Summary: A small polls app in wagtail
Home-page: https://gitlab.com/thelabnyc/wagtail_polls
Author: David Burke
Author-email: david@thelabnyc.com
License: Apache License
Keywords: django wagtail poll
Platform: UNKNOWN
Classifier: Development Status :: 4 - Beta
Classifier: Environment :: Web Environment
Classifier: Framework :: Django
Classifier: Programming Language :: Python
Classifier: Programming Language :: Python :: 3.6
Classifier: Intended Audience :: Developers
Classifier: License :: OSI Approved :: Apache Software License
Requires-Dist: wagtail (>=2.0)
